dpern/__main__.py
dpern/dpern.py
dpern-0.0.3.dist-info/METADATA
dpern-0.0.3.dist-info/WHEEL
dpern-0.0.3.dist-info/top_level.txt
dpern-0.0.3.dist-info/RECORD
