Metadata-Version: 2.1
Name: dpern
Version: 0.0.3
Summary: Describe PERsian Numbers
Home-page: https://github.com/amirashabani/dpern
Author: Amir A. Shabani
Author-email: amirashabani@zoho.com
License: MIT
Platform: UNKNOWN
Classifier: License :: OSI Approved :: MIT License
Classifier: Programming Language :: Python :: 3
Classifier: Programming Language :: Python :: 3.7
